pymed_paperscraper/__init__.py
pymed_paperscraper/api.py
pymed_paperscraper/article.py
pymed_paperscraper/book.py
pymed_paperscraper/helpers.py
pymed_paperscraper/tests/test_article.py
pymed_paperscraper-1.0.4.dist-info/licenses/LICENCE
pymed_paperscraper-1.0.4.dist-info/METADATA
pymed_paperscraper-1.0.4.dist-info/WHEEL
pymed_paperscraper-1.0.4.dist-info/top_level.txt
pymed_paperscraper-1.0.4.dist-info/RECORD
