Metadata-Version: 2.4
Name: pymed_paperscraper
Version: 1.0.4
Summary: Python library for access to PubMed -- fork from archived PyMed
Author-email: Jannis Born <jannis.born@gmx.de>
License: MIT
Project-URL: Homepage, https://github.com/jannisborn/pymed
Keywords: PubMed,Academics,Science,Publication,Search
Classifier: Topic :: Utilities
Classifier: Development Status :: 3 - Alpha
Classifier: Intended Audience :: Science/Research
Classifier: License :: OSI Approved :: MIT License
Classifier: Programming Language :: Python :: 3 :: Only
Classifier: Programming Language :: Python :: 3.8
Classifier: Programming Language :: Python :: 3.9
Classifier: Programming Language :: Python :: 3.10
Classifier: Programming Language :: Python :: 3.11
Requires-Python: >=3.7
License-File: LICENCE
Requires-Dist: requests>=2.20.0
Requires-Dist: tqdm
Provides-Extra: test
Requires-Dist: pytest; extra == "test"
Dynamic: license-file
